nonebot_plugin_vf/__init__.py
nonebot_plugin_vf/api.py
nonebot_plugin_vf-1.3.0.dist-info/LICENSE
nonebot_plugin_vf-1.3.0.dist-info/METADATA
nonebot_plugin_vf-1.3.0.dist-info/WHEEL
nonebot_plugin_vf-1.3.0.dist-info/top_level.txt
nonebot_plugin_vf-1.3.0.dist-info/RECORD
