Metadata-Version: 2.1
Name: nonebot-plugin-vf
Version: 1.3.0
Summary: Nonebot2 plugin
Home-page: https://github.com/snowyfirefly/VirtualFriends
Author: SnowyKami
Author-email: snowykami@outlook.com
License: UNKNOWN
Project-URL: Bug Tracker, https://github.com/snowyfirefly/VirtualFriends
Platform: UNKNOWN
Classifier: Programming Language :: Python :: 3
Classifier: License :: OSI Approved :: MIT License
Classifier: Operating System :: OS Independent
Requires-Python: >=3.6
License-File: LICENSE
